{
  "settings": {
    "flashcardEasyText": "Easy",
    "flashcardGoodText": "Good",
    "flashcardHardText": "Hard",
    "flashcardTags": [
      "#flashcards",
      "#DefinitionCards",
      "#FinanceCards",
      "#SoftwareCards",
      "#PsychCards",
      "#PhysicalHealthCards",
      "#RandomFactCards",
      "#MathCards",
      "#MentalHealthCards",
      "#CareerCards",
      "#PhilosophyCards",
      "#VimCards"
    ],
    "convertFoldersToDecks": false,
    "cardCommentOnSameLine": false,
    "burySiblingCards": true,
    "showContextInCards": false,
    "flashcardHeightPercentage": 100,
    "flashcardWidthPercentage": 100,
    "randomizeCardOrder": true,
    "convertHighlightsToClozes": true,
    "convertBoldTextToClozes": false,
    "convertCurlyBracketsToClozes": false,
    "singleLineCardSeparator": "::",
    "singleLineReversedCardSeparator": ":::",
    "multilineCardSeparator": "?",
    "multilineReversedCardSeparator": "??",
    "editLaterTag": "#edit-later",
    "enableNoteReviewPaneOnStartup": true,
    "tagsToReview": [
      "#review"
    ],
    "noteFoldersToIgnore": [],
    "openRandomNote": false,
    "autoNextNote": true,
    "disableFileMenuReviewOptions": false,
    "maxNDaysNotesReviewQueue": 365,
    "initiallyExpandAllSubdecksInTree": false,
    "baseEase": 250,
    "lapsesIntervalChange": 0.01,
    "easyBonus": 1.3,
    "maximumInterval": 36525,
    "maxLinkFactor": 1,
    "showDebugMessages": true
  },
  "buryDate": "2023-10-16",
  "buryList": [
    "9ee19994362fc",
    "13802be9ca556a",
    "f5f7c89f11044",
    "3ab6b090ed530",
    "19a5ba214a5cb6",
    "1ca9d464c37fdd",
    "146224ccb71e1c",
    "d9853b1c16353",
    "5d4ac9c505992",
    "15aae7a97ceae6",
    "1175a879c7f99a",
    "1f20e061c6e9d1",
    "147f06da2d02c1",
    "fa3727b5df1be",
    "1afbd8a8b7b7fa",
    "571ad3f0144dc",
    "1c1fc446359fd9",
    "1eed3412bac22a",
    "7ed4632bbfb2c",
    "1b76122ae5fd39",
    "1e2078186510c4",
    "ac33a3361f48",
    "8cf676f541fde",
    "16ef2a8b27a398",
    "1683a3eee09940",
    "1e5262ff8a5d86",
    "b2ce8f61bee67",
    "f9c7733638323",
    "124b1eb0333d71",
    "192b06f8f82d9e",
    "9e822c70c8d27",
    "18fb66b130626d",
    "1dc38838937c03",
    "1fb1f4bdff4f9b",
    "10c432d0dd61fe",
    "1d7793232fcd12",
    "f0a38a8020b03",
    "130bcfbd70802f",
    "f72a976068d03",
    "1354310d411958",
    "4276aa931df99",
    "19e3f71cd1e13c",
    "a1dbc53c44baf",
    "1d87506617424",
    "14ec07ac65f6c2",
    "145ae965d2d96e"
  ],
  "historyDeck": "VimCards"
}